{"name":"svg","type":"element","value":"","attributes":{"xmlns":"http://www.w3.org/2000/svg","width":"26","height":"21","version":"1.0"},"children":[{"name":"path","type":"element","value":"","attributes":{"d":"M5 8h15v13H5z"},"children":[]},{"name":"path","type":"element","value":"","attributes":{"fill":"#fff","d":"M7 10h11v9H7z"},"children":[]},{"name":"path","type":"element","value":"","attributes":{"d":"M1.406.594L0 2l4 4h2.813L1.405.594zM24.594 9.594L21 13.188V16l5-5-1.406-1.406z"},"children":[]}]}